orderedattrdict/__init__.py
orderedattrdict/ordereddict.py
orderedattrdict/yamlutils.py
orderedattrdict-1.6.0.dist-info/LICENSE
orderedattrdict-1.6.0.dist-info/METADATA
orderedattrdict-1.6.0.dist-info/WHEEL
orderedattrdict-1.6.0.dist-info/pbr.json
orderedattrdict-1.6.0.dist-info/top_level.txt
orderedattrdict-1.6.0.dist-info/RECORD
