Metadata-Version: 1.1
Name: orderedattrdict
Version: 1.6.0
Summary: OrderedDict with attribute-style access
Home-page: https://github.com/sanand0/orderedattrdict
Author: S Anand
Author-email: root.node@gmail.com
License: MIT
Keywords: ordereddict ordered map attrdict tree conf config configuration yaml json
Platform: UNKNOWN
Classifier: Development Status :: 5 - Production/Stable
Classifier: Intended Audience :: Developers
Classifier: License :: OSI Approved :: MIT License
Classifier: Operating System :: OS Independent
Classifier: Programming Language :: Python
Classifier: Programming Language :: Python :: 2
Classifier: Programming Language :: Python :: 2.7
Classifier: Programming Language :: Python :: 3
Classifier: Programming Language :: Python :: 3.3
Classifier: Programming Language :: Python :: 3.4
Classifier: Programming Language :: Python :: 3.5
Classifier: Programming Language :: Python :: 3.6
Classifier: Topic :: Software Development
Classifier: Topic :: Software Development :: Libraries :: Python Modules
